ILpyTHERMO/__init__.py
ILpyTHERMO/core.py
ILpyTHERMO/utils.py
ilpythermo-0.1.1.dist-info/licenses/LICENSE
ilpythermo-0.1.1.dist-info/METADATA
ilpythermo-0.1.1.dist-info/WHEEL
ilpythermo-0.1.1.dist-info/top_level.txt
ilpythermo-0.1.1.dist-info/RECORD
